floki/__init__.py
floki/agent/__init__.py
floki/agent/base.py
floki/agent/actor/__init__.py
floki/agent/actor/base.py
floki/agent/actor/interface.py
floki/agent/patterns/__init__.py
floki/agent/patterns/openapi/__init__.py
floki/agent/patterns/openapi/react.py
floki/agent/patterns/openapi/tools.py
floki/agent/patterns/react/__init__.py
floki/agent/patterns/react/base.py
floki/agent/patterns/toolcall/__init__.py
floki/agent/patterns/toolcall/base.py
floki/agent/services/__init__.py
floki/agent/services/base.py
floki/agent/services/default.py
floki/agent/services/messaging.py
floki/agent/utils/__init__.py
floki/agent/utils/auth.py
floki/agent/utils/factory.py
floki/agent/utils/message_converter.py
floki/agent/utils/text_printer.py
floki/agent/workflows/__init__.py
floki/agent/workflows/base.py
floki/agent/workflows/llm.py
floki/agent/workflows/random.py
floki/agent/workflows/roundrobin.py
floki/document/__init__.py
floki/document/embedder/__init__.py
floki/document/embedder/base.py
floki/document/embedder/nvidia.py
floki/document/embedder/openai.py
floki/document/embedder/sentence.py
floki/document/fetcher/__init__.py
floki/document/fetcher/arxiv.py
floki/document/fetcher/base.py
floki/document/reader/__init__.py
floki/document/reader/base.py
floki/document/reader/text.py
floki/document/reader/pdf/__init__.py
floki/document/reader/pdf/pymupdf.py
floki/document/reader/pdf/pypdf.py
floki/document/splitter/__init__.py
floki/document/splitter/base.py
floki/document/splitter/text.py
floki/llm/__init__.py
floki/llm/base.py
floki/llm/chat.py
floki/llm/elevenlabs/__init__.py
floki/llm/elevenlabs/client.py
floki/llm/elevenlabs/speech.py
floki/llm/huggingface/__init__.py
floki/llm/huggingface/chat.py
floki/llm/huggingface/client.py
floki/llm/nvidia/__init__.py
floki/llm/nvidia/chat.py
floki/llm/nvidia/client.py
floki/llm/nvidia/embeddings.py
floki/llm/openai/__init__.py
floki/llm/openai/audio.py
floki/llm/openai/chat.py
floki/llm/openai/embeddings.py
floki_ai-0.11.2.dist-info/LICENSE
floki_ai-0.11.2.dist-info/METADATA
floki_ai-0.11.2.dist-info/WHEEL
floki_ai-0.11.2.dist-info/top_level.txt
floki_ai-0.11.2.dist-info/RECORD
