Metadata-Version: 2.2
Name: floki-ai
Version: 0.11.2
Summary: Agentic Workflows Made Simple
Home-page: https://github.com/Cyb3rWard0g/floki
Author: Roberto Rodriguez
License: MIT License
Project-URL: homepage, https://github.com/Cyb3rWard0g/floki
Keywords: LLM,Cybersecurity,AI,Agents
Classifier: Development Status :: 3 - Alpha
Classifier: Intended Audience :: Science/Research
Classifier: License :: OSI Approved :: MIT License
Classifier: Operating System :: POSIX :: Linux
Classifier: Operating System :: OS Independent
Classifier: Operating System :: MacOS
Classifier: Operating System :: POSIX :: Linux
Classifier: Operating System :: Microsoft :: Windows
Classifier: Programming Language :: Python :: 3.10
Classifier: Programming Language :: Python :: 3.11
Classifier: Programming Language :: Python :: 3.12
Requires-Python: >=3.10
License-File: LICENSE
Requires-Dist: pydantic==2.10.5
Requires-Dist: openai==1.59.6
Requires-Dist: openapi-pydantic==0.5.1
Requires-Dist: regex>=2023.12.25
Requires-Dist: Jinja2==3.1.5
Requires-Dist: azure-identity==1.19.0
Requires-Dist: dapr==1.14.0
Requires-Dist: dapr-ext-fastapi==1.14.0
Requires-Dist: dapr-ext-workflow==0.5.0
Requires-Dist: colorama==0.4.6
Requires-Dist: cloudevents==1.11.0
Requires-Dist: pyyaml==6.0.2
Requires-Dist: rich==13.9.4
Requires-Dist: huggingface_hub==0.27.1
Requires-Dist: numpy==2.2.2
Dynamic: home-page
